kr_h/__init__.py
kr_h/kr_h.py
kr_h-0.0.7.dist-info/LICENSE.txt
kr_h-0.0.7.dist-info/METADATA
kr_h-0.0.7.dist-info/WHEEL
kr_h-0.0.7.dist-info/top_level.txt
kr_h-0.0.7.dist-info/RECORD
