Metadata-Version: 2.1
Name: kr-h
Version: 0.0.7
Summary: kraken-helpers
Home-page: https://github.com/tactik8/kr_h
Author: Tactik8
Author-email: info@tactik8.com
License: MIT
Platform: UNKNOWN
Classifier: License :: OSI Approved :: MIT License
Classifier: Programming Language :: Python :: 3
Classifier: Programming Language :: Python :: 3.8
License-File: LICENSE.txt
